{
  "name": "Ernest Cain",
  "age": 53,
  "address": {
    "street": "Apusi Road",
    "city": "Sofatfok",
    "state": "OR",
    "zip": "77486"
  },
  "contact": {
    "phone": "(223) 492-9841",
    "servicePhone": "800114194"
  },
  "birthday": "1998-12-31T00:37:29.041Z",
  "ip": "237.50.132.64",
  "foo": "bar",
  "profile": {
    "about": "Guce peshe upa zazakel esceh niglokmah kicwij idhohveh visardi cif bamagdu gukuv he ekguw ozusuat waipo ansuoce. Awteam huvhaw suhdon tu jodhanem ha jigaif ekorozuh vuzge kofsog nociz netup fag letlap kodap get. Af mo elanikge bo pi vegbade lovrilir il zos aca uhuulula bonmo zovolta fafos uwuho upale. Sic hecfa hujrehdo mikzumi guvkewe rifew fis amci kaj an imeti elaupa. Cawziv jaome elhognu witivpi ibgojfov arked haoloz nadi masizo mu giwibufe vu tozo bipnunwo. Eceupu fevlifati tahmuwev lurdi ukpovar urowup osimizi mo siteoj sal wigtiwem cod vaz.",
    "bio": "Wisbub os lofzun mube rewa zirpubhij rezwibwe rurigigin ikusit wi coalo mapwetfa cuowu iji. Tikinsat haobsol viner ho de wu wemuza octew sof akiba folkefvan wiphu. Fof rumfaec moluhzub tecalfaz kuomce ud ges rulut womhe biada dep gicdaka."
  },
  "apiKey": "faac3d81a3fbfd4f69b37be4d9c494e257a25bcae410afe98fa2f6a4228a2aae",
  "currency": {
    "code": "ALL",
    "name": "Albania Lek"
  }
}