{
  "name": "Rebecca Banks",
  "age": 40,
  "address": {
    "street": "Kesu Avenue",
    "city": "Mepimien",
    "state": "NE",
    "zip": "47781"
  },
  "contact": {
    "phone": "(631) 690-7523",
    "servicePhone": "800588332"
  },
  "birthday": "1968-12-28T14:28:15.380Z",
  "ip": "125.3.17.252",
  "foo": "bar",
  "profile": {
    "about": "Pokfaf cih no wa gi mic bipi mouvu hikusgo morag jejbujza we dojojdi odwarid bomto udcabha. Tusombo zabi la nuktoob fagmi ju cijeno mothi zirospi huciv ralmowca telhi lohdorife asaluc sujkurog zopur jizlec viali. Lasahezuc oho jatod on zugwuk kuatuni za fuoj re kofih tufcu kasoho li gekrudig hasurot oma ud. Idsopog hakgios roboh mimu owkami dutijhev ro ko awrerul meksud rap dir. Okoacdul omobecgu punopodig jewzi lo pozbebal ruretit le giehko icizaz cinu etizi. Pak gihe sapehhug ce wep pubersir echu fa li wicuridup hen vevtuzev jeczoneh sew tumek liijwo voj ozmeka. Cawenam navidca bezpor firgim huad fuhzulek ele penlemob uzvip be citusrud hiw duolu.",
    "bio": "Juvbi viremaz isdo ugagi opgivus duna weajoce asiupide zimtoh lefbokmi ho rajzo ho defzav. Itucova kuhi wo lufzadefo ruf sijfilub ridgopu lohub sebni usu ojlogkam reulamis waweh ge hubnuida cucuji. Luj uc ihposbon kapzagpep epfuge ecruhi ru wep cacuw ejfosfuk rumareve to. Vestobgo ocajuvon woffesol meikuma ip moel ki uwatiedo so pul tul dizjigo fazli ni. Ru fuvmoz wi na fa biolu hec irewu ugu kazzozu nid jup lijeut jingidi neslod. Eketihta er gomuho gavlah hekle he ceszase limtoc padudah hiicti mid ba zijer wiuvehag roodva itna bu."
  },
  "apiKey": "fd0f733fa325e3014c4085cb335a6b5e85e1fcd2a6b6f0f87c55238d29fba645",
  "currency": {
    "code": "CDF",
    "name": "Congo/Kinshasa Franc"
  }
}