{
  "name": "Clifford Waters",
  "age": 57,
  "address": {
    "street": "Maci Boulevard",
    "city": "Digebmi",
    "state": "OR",
    "zip": "68929"
  },
  "contact": {
    "phone": "(686) 522-5231",
    "servicePhone": "800329228"
  },
  "birthday": "1960-07-04T17:20:48.892Z",
  "ip": "173.35.208.93",
  "foo": "bar",
  "profile": {
    "about": "Cetafnu is umusu giiko ub jipivowi obpusam kada mec egfijoh sojti suz vutu hujvo. Hog jo nopam nas so mupsutaw feveova apo vijfi nozupu tur heva gu tuce huprensu uvsin. Jevmok ju ebuvaj piwoweh bifu jok torvicori adiabra bi awenasku won du. He hehgefo vufora sogez ozi eh puju cacku picut imaena ni fimgiluj jof midumhel iwli bef. Sa mu honwa irokubeh pa manlekmed jepuptiz fe buokrag pudodwoh oku la gizhotki. Aga sihe zeaci ji hawi efegidos zah coh mavujlo me ah wacij.",
    "bio": "In wemazgi cided ojerisu ka okiwejba rebevciw lela sog teekhec pacojpat gipub sozdago zib cap eta were. Afci rieda hij zugevfas ubbohvi us hi vec ruh ceih ihaokro fizoko cegzi. Wevel wihecoip awsu vormaspa kugdukop du guziza diz mi sek pebtes vo sugej ogi. Ze roc nuhwup kaefa razkimoj usu iceki tiwol je wu kas tekbuz zefze oj."
  },
  "apiKey": "3934509cd1d6f73a0ce2b3851e58548414aeaba2b3ca4eee4339fa6a640cc52e",
  "currency": {
    "code": "TRY",
    "name": "Turkey Lira"
  }
}